mixin/forms.py
django_mixin-1.0.0.dist-info/LICENSE
django_mixin-1.0.0.dist-info/METADATA
django_mixin-1.0.0.dist-info/WHEEL
django_mixin-1.0.0.dist-info/top_level.txt
django_mixin-1.0.0.dist-info/RECORD
