Metadata-Version: 2.1
Name: django-mixin
Version: 1.0.0
Summary: Reusable, generic mixins for Django
Home-page: https://github.com/null-none/django-mixin/
Author: Kenneth Love <kenneth@brack3t.com>, Chris Jones <chris@brack3t.com>, Kalinin Dmitry <kalinin.mitko@gmail.com>
Author-email: kalinin.mitko@gmail.com
License: BSD
Keywords: django,views,forms,mixins
Platform: UNKNOWN
Classifier: Programming Language :: Python
Classifier: Topic :: Software Development :: Libraries :: Python Modules
Classifier: License :: OSI Approved :: BSD License
Classifier: Environment :: Web Environment
Classifier: Development Status :: 5 - Production/Stable
Classifier: Programming Language :: Python :: 2.7
Classifier: Programming Language :: Python :: 3.4
Classifier: Programming Language :: Python :: 3.5
Classifier: Programming Language :: Python :: 3.6
Classifier: Framework :: Django
Classifier: Framework :: Django :: 1.11
Classifier: Framework :: Django :: 2.0
License-File: LICENSE
Requires-Dist: Django (>=1.11.0)
Requires-Dist: six
